muse_psf/__init__.py
muse_psf/fitting/__init__.py
muse_psf/fitting/psf_fitting.py
muse_psf/utils/__init__.py
muse_psf/utils/paths.py
muse_psf-0.0.3.dist-info/LICENSE
muse_psf-0.0.3.dist-info/METADATA
muse_psf-0.0.3.dist-info/WHEEL
muse_psf-0.0.3.dist-info/top_level.txt
muse_psf-0.0.3.dist-info/RECORD
