Metadata-Version: 2.1
Name: muse-psf
Version: 0.0.3
Summary: muse_psf
Home-page: https://github.com/m-vegap/muse-psf
Author: m-vegap (Macarena Vega)
Author-email: <m.vega.pallauta@gmail.com>
License: MIT
Keywords: python adaptative optics muse psf
Platform: UNKNOWN
Classifier: Development Status :: 1 - Planning
Classifier: Intended Audience :: Developers
Classifier: Programming Language :: Python :: 3
Classifier: Operating System :: Unix
Classifier: Operating System :: MacOS :: MacOS X
Classifier: Operating System :: Microsoft :: Windows
License-File: LICENSE
Requires-Dist: numpy
Requires-Dist: astropy
Requires-Dist: photutils
